overleaf_mcp/__init__.py
overleaf_mcp/__main__.py
overleaf_mcp/mh_overleaf.py
overleaf_mcp-0.1.6.dist-info/METADATA
overleaf_mcp-0.1.6.dist-info/WHEEL
overleaf_mcp-0.1.6.dist-info/entry_points.txt
overleaf_mcp-0.1.6.dist-info/top_level.txt
overleaf_mcp-0.1.6.dist-info/RECORD
