Metadata-Version: 2.4
Name: overleaf-mcp
Version: 0.1.6
Summary: MCP server for Overleaf projects
Project-URL: Homepage, https://github.com/M-H-Amini/Overleaf-MCP-Server
Project-URL: Repository, https://github.com/M-H-Amini/Overleaf-MCP-Server
Project-URL: Issues, https://github.com/M-H-Amini/Overleaf-MCP-Server/issues
Requires-Python: >=3.10
Requires-Dist: mcp[cli]>=1.17.0
Requires-Dist: python-dotenv>=1.1.1
